AutoTasker/__init__.py
AutoTasker/main.py
tests/__init__.py
AutoTasker-1.1.1.dist-info/LICENSE
AutoTasker-1.1.1.dist-info/METADATA
AutoTasker-1.1.1.dist-info/WHEEL
AutoTasker-1.1.1.dist-info/entry_points.txt
AutoTasker-1.1.1.dist-info/top_level.txt
AutoTasker-1.1.1.dist-info/RECORD
