Metadata-Version: 2.1
Name: AutoTasker
Version: 1.1.1
Summary: AutoTasker is a console application designed to simplify and automate repetitive tasks without the need for programming skills. With AutoTasker, you can easily set up a variety of automated tasks, saving you time and effort in your daily activities.
Home-page: https://github.com/mramosg7/AutoTasker
Author: mramosg7
Author-email: marioramos.cobisa@gmail.com
License: MIT
License-File: LICENSE
Requires-Dist: setuptools ==70.2.0
